twat_ez/__init__.py
twat_ez/__version__.py
twat_ez/py_needs.py
twat_ez-2.7.5.dist-info/METADATA
twat_ez-2.7.5.dist-info/WHEEL
twat_ez-2.7.5.dist-info/entry_points.txt
twat_ez-2.7.5.dist-info/licenses/LICENSE
twat_ez-2.7.5.dist-info/RECORD
