Metadata-Version: 2.4
Name: twat-ez
Version: 2.7.5
Summary: Easy and convenient utilities for the twat ecosystem
Project-URL: Documentation, https://github.com/twardoch/twat-ez#readme
Project-URL: Issues, https://github.com/twardoch/twat-ez/issues
Project-URL: Source, https://github.com/twardoch/twat-ez
Author-email: Adam Twardoch <adam+github@twardoch.com>
License-Expression: MIT
License-File: LICENSE
Keywords: convenience,productivity,twat,utilities
Classifier: Development Status :: 4 - Beta
Classifier: Programming Language :: Python
Classifier: Programming Language :: Python :: 3.10
Classifier: Programming Language :: Python :: 3.11
Classifier: Programming Language :: Python :: 3.12
Classifier: Programming Language :: Python :: Implementation :: CPython
Classifier: Programming Language :: Python :: Implementation :: PyPy
Requires-Python: >=3.10
Requires-Dist: twat>=1.8.1
Provides-Extra: all
Requires-Dist: twat>=1.8.1; extra == 'all'
Provides-Extra: dev
Requires-Dist: mypy>=1.15.0; extra == 'dev'
Requires-Dist: pre-commit>=4.1.0; extra == 'dev'
Requires-Dist: pyupgrade>=3.19.1; extra == 'dev'
Requires-Dist: ruff>=0.9.6; extra == 'dev'
Provides-Extra: test
Requires-Dist: pytest-cov>=6.0.0; extra == 'test'
Requires-Dist: pytest>=8.3.5; extra == 'test'
